stocksdata/__init__.py
stocksdata/algorithms.py
stocksdata/buzz.py
stocksdata/economy.py
stocksdata/exchanges.py
stocksdata/financials.py
stocksdata/indicators.py
stocksdata/indices.py
stocksdata/screeners.py
stocksdata/search.py
stocksdata/similarity.py
stocksdata/stock.py
stocksdata/valuation.py
stocksdata/yahoo_finance.py
stocksdata/util/__init__.py
stocksdata/util/get.py
stocksdata/util/ttlcache.py
lattice_stocks_data-1.1.0.dist-info/LICENSE
lattice_stocks_data-1.1.0.dist-info/METADATA
lattice_stocks_data-1.1.0.dist-info/WHEEL
lattice_stocks_data-1.1.0.dist-info/top_level.txt
lattice_stocks_data-1.1.0.dist-info/RECORD
